sorting_techniques/__init__.py
sorting_techniques/_utils.py
sorting_techniques/bogo_sort.py
sorting_techniques/bubble_sort.py
sorting_techniques/counting_sort.py
sorting_techniques/heap_sort.py
sorting_techniques/insertion_sort.py
sorting_techniques/merge_sort.py
sorting_techniques/quick_sort.py
sorting_techniques/radix_sort_lsd.py
sorting_techniques/selection_sort.py
sorting_techniques-1.0.5.dist-info/LICENSE
sorting_techniques-1.0.5.dist-info/METADATA
sorting_techniques-1.0.5.dist-info/WHEEL
sorting_techniques-1.0.5.dist-info/top_level.txt
sorting_techniques-1.0.5.dist-info/RECORD
