Metadata-Version: 2.2
Name: sorting-techniques
Version: 1.0.5
Summary: A Python package with modular sorting algorithm implementations.
Home-page: https://github.com/Hariesh28/Sorting-Algorithms-Library
Author: Hariesh R
Author-email: hariesh28606@gmail.com
Keywords: sorting algorithms,python,data structures
Classifier: Programming Language :: Python :: 3
Classifier: License :: OSI Approved :: GNU General Public License v3 (GPLv3)
Classifier: Operating System :: OS Independent
Requires-Python: >=3.9
License-File: LICENSE
Dynamic: author
Dynamic: author-email
Dynamic: classifier
Dynamic: description
Dynamic: description-content-type
Dynamic: home-page
Dynamic: keywords
Dynamic: requires-python
Dynamic: summary
